discord_ui/__init__.py
discord_ui/client.py
discord_ui/cogs.py
discord_ui/components.py
discord_ui/enums.py
discord_ui/errors.py
discord_ui/http.py
discord_ui/listener.py
discord_ui/override.py
discord_ui/receive.py
discord_ui/tools.py
discord_ui/slash/__init__.py
discord_ui/slash/errors.py
discord_ui/slash/ext.py
discord_ui/slash/http.py
discord_ui/slash/tools.py
discord_ui/slash/types.py
discord_ui/slash/ext/__init__.py
discord_ui/slash/ext/builder.py
discord_ui/slash/ext/command_decorators.py
discord_ui-5.1.5.dist-info/LICENSE
discord_ui-5.1.5.dist-info/METADATA
discord_ui-5.1.5.dist-info/WHEEL
discord_ui-5.1.5.dist-info/top_level.txt
discord_ui-5.1.5.dist-info/RECORD
