Metadata-Version: 2.1
Name: discord-ui
Version: 5.1.5
Summary: A disord.py extension for discord's ui/interaction features
Home-page: https://github.com/discord-py-ui/discord-ui/
Author: 404kuso, RedstoneZockt
Author-email: bellou9022@gmail.com, redstoneprofihd@gmail.com
License: UNKNOWN
Project-URL: Documentation, https://discord-ui.rtfd.io/en/latest/
Project-URL: Issue tracker, https://github.com/discord-py-ui/discord-ui/issues
Platform: UNKNOWN
Classifier: Programming Language :: Python :: 3
Classifier: Intended Audience :: Developers
Classifier: Natural Language :: English
Classifier: Operating System :: OS Independent
Classifier: Programming Language :: Python :: 3.6
Classifier: Programming Language :: Python :: 3.7
Classifier: Programming Language :: Python :: 3.8
Classifier: Programming Language :: Python :: 3.9
Classifier: Topic :: Internet
Classifier: Topic :: Software Development :: Libraries
Classifier: Topic :: Software Development :: Libraries :: Python Modules
Classifier: Topic :: Utilities
Requires-Python: >=3.6
License-File: LICENSE
